simplePyQt/__init__.py
simplePyQt/__main__.py
simplePyQt/builder.py
simplePyQt/constants.py
simplePyQt/header.py
simplePyQt/searthSignals.py
simplePyQt/supportedSignals.py
simplePyQt/utils.py
simplePyQt-0.0.1.dist-info/LICENSE.md
simplePyQt-0.0.1.dist-info/METADATA
simplePyQt-0.0.1.dist-info/WHEEL
simplePyQt-0.0.1.dist-info/entry_points.txt
simplePyQt-0.0.1.dist-info/top_level.txt
simplePyQt-0.0.1.dist-info/RECORD
